emcfsys/__init__.py
emcfsys/_reader.py
emcfsys/_sample_data.py
emcfsys/_version.py
emcfsys/_widget.py
emcfsys/_writer.py
emcfsys/napari.yaml
emcfsys/EMCellFiner/hat/models/hat_arch.py
emcfsys/EMCellFiner/hat/models/hat_model.py
emcfsys/EMCellFiner/hat/models/img_utils.py
emcfsys/EMCellFiner/hat/models/inference_hat.py
emcfsys/EMCellFound/inference.py
emcfsys/EMCellFound/train.py
emcfsys/EMCellFound/datasets/segmentation2D.py
emcfsys/EMCellFound/metrics/metrics.py
emcfsys/EMCellFound/models/BackboneWrapper.py
emcfsys/EMCellFound/models/DeepLabv3Plus.py
emcfsys/EMCellFound/models/EMCellFoundViT.py
emcfsys/EMCellFound/models/PSPNet.py
emcfsys/EMCellFound/models/UNet.py
emcfsys/EMCellFound/models/UperNet.py
emcfsys/EMCellFound/models/backbone_registry.py
emcfsys/EMCellFound/models/model_factory.py
emcfsys/EMCellFound/transforms/augmentations.py
emcfsys/EMCellFound/transforms/transforms.py
emcfsys/EMCellFound/utils/checkpoint.py
emcfsys/dataset_transform/label2semanticseg.py
emcfsys/test_imgs/test_img.tif
emcfsys-0.0.6.dist-info/licenses/LICENSE
emcfsys-0.0.6.dist-info/METADATA
emcfsys-0.0.6.dist-info/WHEEL
emcfsys-0.0.6.dist-info/entry_points.txt
emcfsys-0.0.6.dist-info/top_level.txt
emcfsys-0.0.6.dist-info/RECORD
