Metadata-Version: 2.4
Name: emcfsys
Version: 0.0.6
Summary: Towards foundation models for EM images analysis. EMCellFiner and EMCellFound are two foundation models trained based on a 4 million EM images dataset.
Author: ZeyuYu
Author-email: zeyu_yu@zju.edu.cn
License: 
Classifier: Development Status :: 2 - Pre-Alpha
Classifier: Framework :: napari
Classifier: Intended Audience :: Developers
Classifier: License :: OSI Approved :: GNU General Public License v3 (GPLv3)
Classifier: Operating System :: OS Independent
Classifier: Programming Language :: Python
Classifier: Programming Language :: Python :: 3
Classifier: Programming Language :: Python :: 3 :: Only
Classifier: Programming Language :: Python :: 3.9
Classifier: Programming Language :: Python :: 3.10
Classifier: Programming Language :: Python :: 3.11
Classifier: Programming Language :: Python :: 3.12
Classifier: Programming Language :: Python :: 3.13
Classifier: Topic :: Scientific/Engineering :: Image Processing
Requires-Python: >=3.9
License-File: LICENSE
Requires-Dist: numpy
Requires-Dist: magicgui
Requires-Dist: qtpy
Requires-Dist: scikit-image
Requires-Dist: scipy
Provides-Extra: all
Requires-Dist: napari[all]; extra == "all"
Dynamic: license-file
